LICENSE
MANIFEST.in
README.rst
setup.py
django_supermigrate.egg-info/PKG-INFO
django_supermigrate.egg-info/SOURCES.txt
django_supermigrate.egg-info/dependency_links.txt
django_supermigrate.egg-info/top_level.txt
supermigrate/__init__.py
supermigrate/utils.py
supermigrate/database_routers/__init__.py
supermigrate/database_routers/default.py
supermigrate/management/__init__.py
supermigrate/management/commands/__init__.py
supermigrate/management/commands/supermigrate.py