Metadata-Version: 1.1
Name: django-supermigrate
Version: 0.5
Summary: package to manage migrations on production and development environment simultaneously
Home-page: https://github.com/paytm/django-supermigrate
Author: Shrey Agarwal, Taranjeet Singh
Author-email: shrey.agarwal@paytm.com, reachtotj@gmail.com
License: MIT License
Platform: UNKNOWN
Classifier: Development Status :: 3 - Alpha
Classifier: Environment :: Web Environment
Classifier: Framework :: Django :: 1.8
Classifier: Intended Audience :: Developers
Classifier: License :: OSI Approved :: MIT License
Classifier: Operating System :: OS Independent
Classifier: Programming Language :: Python
Classifier: Natural Language :: English
Classifier: Programming Language :: Python :: 2.7
Classifier: Programming Language :: Python :: 3.4
Classifier: Framework :: Django :: 1.8
Classifier: Topic :: Internet :: WWW/HTTP
